appomatic_mptt
